alicetools/__init__.py
alicetools/mota.py
alicetools-0.0.3.data/scripts/mota.py
alicetools-0.0.3.dist-info/METADATA
alicetools-0.0.3.dist-info/WHEEL
alicetools-0.0.3.dist-info/entry_points.txt
alicetools-0.0.3.dist-info/license.txt
alicetools-0.0.3.dist-info/top_level.txt
alicetools-0.0.3.dist-info/RECORD
