Metadata-Version: 2.1
Name: alicetools
Version: 0.0.3
Summary: Tools developped for ALICe platform.
Home-page: https://github.com/WyssCenter/MOTA
Author: Jules Scholler
Author-email: jules.scholler@wysscenter.ch
License: LIMITED LICENSE AGREEMENT
Keywords: cell mapping,atlas
Platform: UNKNOWN
Classifier: Development Status :: 1 - Planning
Classifier: Intended Audience :: Developers
Classifier: Programming Language :: Python :: 3
License-File: license.txt
Requires-Dist: numpy
Requires-Dist: tqdm
Requires-Dist: pandas
Requires-Dist: scikit-image
Requires-Dist: allensdk
